CHANGELOG.md
LICENSE
MANIFEST.in
README.rst
setup.py
magic/__init__.py
magic/error_urls.py
magic/gifAPI.py
magic/imageGen.py
magic/magic.py
magic/memeAPI.py
markdown_magic.egg-info/PKG-INFO
markdown_magic.egg-info/SOURCES.txt
markdown_magic.egg-info/dependency_links.txt
markdown_magic.egg-info/requires.txt
markdown_magic.egg-info/top_level.txt