Metadata-Version: 1.1
Name: markdown-magic
Version: 1.1
Summary: A Python-Markdown plugin for creating memes and finding the best-fitting gifs for your posts.
Home-page: https://github.com/RadhikaG/markdown-magic
Author: Radhika Ghosal
Author-email: radhikaghosal@gmail.com
License: MIT
Keywords: markdown,markup,memes,gifs,plugin
Platform: UNKNOWN
Classifier: Programming Language :: Python
Classifier: Development Status :: 4 - Beta
Classifier: Environment :: Plugins
Classifier: Intended Audience :: Developers
Classifier: License :: OSI Approved :: MIT License
Classifier: Operating System :: OS Independent
Classifier: Topic :: Software Development :: Libraries :: Python Modules
Classifier: Topic :: Text Processing :: Markup
